{"sigmets": [{"fir": "AYPM PORT MORESBY", "hazard": "TS", "qual": "EMBD", "base": null, "top": 47000, "from": 1783692120, "to": 1784052120, "series": "1", "raw": "WSNG20 AYPY 101408\nAYPM SIGMET 1 VALID 101402/141802 AYPY-\nAYPM PORT MORESBY FIR EMBD TS OBS WI S0005 E14603 - S0004 E15539 -\nS0344 E15513 - S0347 E14923 - S0005 E14603 TOP FL470 MOV SW 10KT NC \n="}, {"fir": "FAJO JOHANNESBURG OCEANIC", "hazard": "TS", "qual": "EMBD", "base": null, "top": 36000, "from": 1784023200, "to": 1784037600, "series": "E01", "raw": "WSZA21 FAOR 141019\nFAJO SIGMET E01 VALID 141000/141400 FAOR-\nFAJO JOHANNESBURG OCEANIC FIR EMBD TS FCST WI\nS2750 E03500 - S3000 E04000 - S3000 E04156 - S3043 E04159 -\nS3116 E03540 - S3253 E03443 - S3200 E03347 - S3154 E03239 -\nS3025 E03332 TOP FL360="}, {"fir": "FAJO JOHANNESBURG OCEANIC", "hazard": "TURB", "qual": "SEV", "base": 14000, "top": 39000, "from": 1784023860, "to": 1784037600, "series": "A01", "raw": "WSZA21 FAOR 141029\nFAJO SIGMET A01 VALID 141011/141400 FAOR-\nFAJO JOHANNESBURG OCEANIC FIR SEV TURB FCST WI\nS4039 E00738 - S4040 E01244 - S4217 E01327 - S4228 E00644 FL140/390="}, {"fir": "VGFR DHAKA", "hazard": "TS", "qual": "EMBD", "base": null, "top": 46000, "from": 1784016000, "to": 1784037600, "series": "03", "raw": "WSBW20 VGHS 140730\nVGFR SIGMET 03 VALID 140800/141400 VGHS-\nVGFR DHAKA FIR EMBD TS FCST ENTIRE FIR TOP FL460 MOV SW 15KT NC="}, {"fir": "SEFG GUAYAQUIL", "hazard": "VA", "qual": "REVENTADOR", "base": 0, "top": 15000, "from": 1784017260, "to": 1784038860, "series": "1", "raw": "WVEQ31 SEQU 140821\nSEFG SIGMET 1 VALID 140821/141421 SEGU-\nSEFG GUAYAQUIL FIR VA ERUPTION MT REVENTADOR PSN S0004 W07739\nVA CLD OBS AT 0730Z WI N0003 W07747 - N0002 W07746 - N0000 W07747 - \nN0001 W07749 - N0003 W07747 SFC/FL150 MOV NW 15KT \nFCST AT 1330Z WI N0002 W07750 - S0004 W07739 - S0005 W07739 - S0000 \nW07752 - N0002 W07750="}, {"fir": "YMMM MELBOURNE", "hazard": "MTW", "qual": "SEV", "base": 4000, "top": 14000, "from": 1784026800, "to": 1784037600, "series": "K03", "raw": "WSAU21 YMRF 140902\nYMMM SIGMET K03 VALID 141100/141400 YMRF-\nYMMM MELBOURNE FIR SEV MTW FCST WI S4200 E14730 - S4320 E14720 -\nS4330 E14700 - S4330 E14630 - S4230 E14610 - S4200 E14650 - S4140\nE14610 - S4130 E14630 4000FT/FL140 STNR INTSF="}, {"fir": "MHCC CENTRAL AMERICAN", "hazard": "VA", "qual": "", "base": 0, "top": 14000, "from": 1784022600, "to": 1784044200, "series": "B2", "raw": "WVHO31 MHTG 140950\nMHTG SIGMET B2 VALID 140950/141550 MHTG-\nMHCC CENTRAL AMERICAN FIR VA SANTA MARIA PSN N1445 W09133\nVA CLD OBS AT 0850Z SFC/FL140 N1449 W09143 - N1446 W09132\n- N1445 W09132 - N1445 W09143 - N1449 W09143 MOV W 15KT \nFCST 1500Z VA CLD SFC/FL140 N1449 W09143- N1446 W09132\n - N1445 W09132 - N1445 W09143 -N1449 W09143="}, {"fir": "FIMM MAURITIUS", "hazard": "TS", "qual": "EMBD", "base": null, "top": 41000, "from": 1784022300, "to": 1784036700, "series": "B03", "raw": "WSMA31 FIMP 140945\nFIMM SIGMET B03 VALID 140945/141345 FIMP-\nFIMM MAURITIUS FIR EMBD TS OBS AT 0930Z N OF LINE S0600 E06600 -\nS0800 E06500 - S0811 E06000 TOP ABV FL410 STNR NC="}, {"fir": "SAEF EZEIZA", "hazard": "ICE", "qual": "SEV", "base": 8000, "top": 18000, "from": 1784022300, "to": 1784036700, "series": "B1", "raw": "WSAG31 SABE 140945\nSAEF SIGMET B1 VALID 140945/141345 SABE-\nSAEF EZEIZA FIR SEV ICE FCST AT 0945Z\nWI S3814 W06958 - S4004 W07059 - S4057 W06853 - S4121 W07030 - S4152\nW07116 - S4106 W07139 - S3858 W07126 - S3814 W06958 FL080/180 MOV SE \n10KT NC="}, {"fir": "FIMM MAURITIUS", "hazard": "ICE", "qual": "SEV", "base": 6000, "top": 10000, "from": 1784022300, "to": 1784036700, "series": "A03", "raw": "WSMA31 FIMP 140945\nFIMM SIGMET A03 VALID 140945/141345 FIMP-\nFIMM MAURITIUS FIR SEV ICE FCST E OF LINE S3230 E07500 - S3200 E06300\n - S3730 E05812 - S3830 E07500 FL 060/100 STNR NC="}, {"fir": "FAJO JOHANNESBURG OCEANIC", "hazard": "TS", "qual": "EMBD", "base": null, "top": 36000, "from": 1784023200, "to": 1784037600, "series": "F01", "raw": "WSZA21 FAOR 141009\nFAJO SIGMET F01 VALID 141000/141400 FAOR-\nFAJO JOHANNESBURG OCEANIC FIR EMBD TS OBS WI\nS3154 E03238 - S3201 E03347 - S3252 E03442 - S3609 E03129 -\nS3631 E02856 - S3609 E02850 - S3300 E03200 TOP FL360="}, {"fir": "FACA CAPE TOWN", "hazard": "TS", "qual": "EMBD", "base": null, "top": 36000, "from": 1784023200, "to": 1784037600, "series": "A01", "raw": "WSZA21 FAOR 141007\nFACA SIGMET A01 VALID 141000/141400 FAOR-\nFACA CAPE TOWN FIR EMBD TS OBS WI\nS3219 E03046 - S3300 E03200 - S3609 E02850 - S3406 E02817 -\nS3219 E03046 TOP FL360="}, {"fir": "FAJA JOHANNESBURG", "hazard": "TS", "qual": "EMBD", "base": null, "top": 36000, "from": 1784023200, "to": 1784037600, "series": "D01", "raw": "WSZA21 FAOR 141008\nFAJA SIGMET D01 VALID 141000/141400 FAOR-\nFAJA JOHANNESBURG FIR EMBD TS OBS WI\nS3148 E03130 - S3154 E03238 - S3300 E03200 - S3219 E03046 TOP FL360="}, {"fir": "FAJA JOHANNESBURG", "hazard": "TURB", "qual": "SEV", "base": 24000, "top": 34000, "from": 1784023860, "to": 1784037600, "series": "A01", "raw": "WSZA21 FAOR 141028\nFAJA SIGMET A01 VALID 141011/141400 FAOR-\nFAJA JOHANNESBURG FIR SEV TURB FCST WI\nS2208 E02946 - S2223 E03018 - S2217 E03054 - S2222 E03117 -\nS2310 E03132 - S2329 E03132 - S2400 E03154 - S2420 E03200 -\nS2502 E03203 - S2528 E03200 - S2536 E03200 - S2548 E03155 -\nS2557 E03158 - S2600 E03205 - S2619 E03204 - S2630 E03207 -\nS2643 E03207 - S2700 E03200 - S2650 E03253 - S2734 E03427 -\nS2748 E03406 - S2537 E02535 - S2537 E02537 - S2455 E02552 -\nS2440 E02610 - S2438 E02623 - S2418 E02650 - S2338 E02700 -\nS2324 E02732 - S2300 E02800 - S2250 E02802 - S2234 E02819 -\nS2227 E02855 - S2213"}, {"fir": "FAJO JOHANNESBURG OCEANIC", "hazard": "TURB", "qual": "SEV", "base": 24000, "top": 30000, "from": 1784023920, "to": 1784037600, "series": "D01", "raw": "WSZA21 FAOR 141032\nFAJO SIGMET D01 VALID 141012/141400 FAOR-\nFAJO JOHANNESBURG OCEANIC FIR SEV TURB FCST WI\nS4250 E00509 - S4331 E00510 - S4458 E00001 - S4604 W00740 -\nS4459 W00801 - S4446 W00351 - S4252 E00130 FL240/300="}, {"fir": "FAJO JOHANNESBURG OCEANIC", "hazard": "TURB", "qual": "SEV", "base": 34000, "top": 45000, "from": 1784023920, "to": 1784037600, "series": "C01", "raw": "WSZA21 FAOR 141031\nFAJO SIGMET C01 VALID 141012/141400 FAOR-\nFAJO JOHANNESBURG OCEANIC FIR SEV TURB FCST WI\nS3656 W00419 - S3858 E00150 - S4102 E00325 - S4314 W00003 -\nS4343 W00414 - S4311 W00629 - S3943 W00753 - S3804 W00456 FL340/450="}, {"fir": "FAJO JOHANNESBURG OCEANIC", "hazard": "TURB", "qual": "SEV", "base": 10000, "top": 45000, "from": 1784023920, "to": 1784037600, "series": "B01", "raw": "WSZA21 FAOR 141030\nFAJO SIGMET B01 VALID 141012/141400 FAOR-\nFAJO JOHANNESBURG OCEANIC FIR SEV TURB FCST WI\nS3627 W00757 - S3808 W00455 - S3943 W00756 - S3940 W01000 -\nS3657 W01000 FL100/450="}, {"fir": "FAJO JOHANNESBURG OCEANIC", "hazard": "TURB", "qual": "SEV", "base": 14000, "top": 18000, "from": 1784023920, "to": 1784037600, "series": "G01", "raw": "WSZA21 FAOR 141033\nFAJO SIGMET G01 VALID 141012/141400 FAOR-\nFAJO JOHANNESBURG OCEANIC FIR SEV TURB FCST WI\nS4847 E02204 - S4855 E02244 - S5005 E02244 - S5019 E02210 -\nS5008 E02133 - S4900 E02137 FL140/180="}, {"fir": "UNKL KRASNOYARSK", "hazard": "TS", "qual": "EMBD", "base": null, "top": 40000, "from": 1784030400, "to": 1784041200, "series": "8", "raw": "WSRA31 RUKR 141018\nUNKL SIGMET 8 VALID 141200/141500 UNKL-\nUNKL KRASNOYARSK FIR EMBD TSGR FCST S OF LINE N5721 E08810 - N5727\nE09732 TOP FL400 STNR NC="}, {"fir": "UNKL KRASNOYARSK", "hazard": "TS", "qual": "OBSC", "base": null, "top": null, "from": 1784030400, "to": 1784041200, "series": "9", "raw": "WSRA31 RUKR 141019\nUNKL SIGMET 9 VALID 141200/141500 UNKL-\nUNKL KRASNOYARSK FIR OBSC TS FCST S OF LINE N6327 E08448 - N6252\nE09337 - N6728 E09432 - N6700 E10655 AND N OF LINE N5721 E08810 -\nN5727 E09732 TOP FL390 STNR NC="}, {"fir": "SAVF COMODORO RIVADAVIA", "hazard": "TURB", "qual": "SEV", "base": 25000, "top": 35000, "from": 1784024580, "to": 1784038980, "series": "A2", "raw": "WSAG31 SABE 141023\nSAVF SIGMET A2 VALID 141023/141423 SABE-\nSAVF COMODORO RIVADAVIA FIR SEV TURB FCST AT 1023Z\nWI S4301 W07119 - S4401 W06645 - S4314 W05409 - S4549 W05303 - S4604\nW06423 - S4628 W07127 - S4301 W07119 FL250/350 STNR NC="}, {"fir": "UNKL KRASNOYARSK", "hazard": "TS", "qual": "EMBD", "base": null, "top": 39000, "from": 1784030400, "to": 1784041200, "series": "10", "raw": "WSRA31 RUKR 141020\nUNKL SIGMET 10 VALID 141200/141500 UNKL-\nUNKL KRASNOYARSK FIR EMBD TS FCST WI N7030 E09000 - N6728 E09432 -\nN6252 E09337 - N6327 E08448 - N6633 E08247 - N6806 E08600 - N6803\nE08739 - N6919 E08719 - N6923 E08822 - N6945 E08730 - N7030 E09000\nTOP FL390 STNR NC="}, {"fir": "UNKL KRASNOYARSK", "hazard": "TS", "qual": "OBSC", "base": null, "top": 39000, "from": 1784030400, "to": 1784041200, "series": "11", "raw": "WSRA31 RUKR 141022\nUNKL SIGMET 11 VALID 141200/141500 UNKL-\nUNKL KRASNOYARSK FIR OBSC TS FCST WI N6945 E08730 - N6923 E08822 -\nN6919 E08719 - N6803 E08739 - N6806 E08600 - N6934 E08617 - N6945\nE08730 TOP FL390 STNR NC="}, {"fir": "SAVF COMODORO RIVADAVIA", "hazard": "ICE", "qual": "SEV", "base": 3000, "top": 14000, "from": 1784024760, "to": 1784039160, "series": "B2", "raw": "WSAG31 SABE 141026\nSAVF SIGMET B2 VALID 141026/141426 SABE-\nSAVF COMODORO RIVADAVIA FIR SEV ICE FCST AT 1026Z\nWI S5450 W05933 - S5223 W06251 - S5107 W06248 - S4902 W05833 - S4927\nW05409 - S4801 W04911 - S5225 W04800 - S5505 W04911 - S5450 W05933 \nFL030/140 MOV E 10KT NC="}, {"fir": "UATT AKTOBE", "hazard": "TS", "qual": "EMBD", "base": null, "top": null, "from": 1784025000, "to": 1784037600, "series": "1", "raw": "WSKZ31 UATT 141026\nUATT SIGMET 1 VALID 141030/141400 UATT-\nUATT AKTOBE FIR EMBD TSGR FCST N OF N48 AND E OF E052 AND W OF E060\nTOP FL380 MOV NE 20KMH NC="}, {"fir": "OPKR KARACHI", "hazard": "TS", "qual": "EMBD", "base": null, "top": 38000, "from": 1784025000, "to": 1784039400, "series": "1", "raw": "WSPK31 OPKC 141015\nOPKR SIGMET 1 VALID 141030/141430 OPKC-\nOPKR KARACHI FIR ISOL EMBD TS FCST N OF N2730 E OF E066 TOP \nFL380 MOV SE INTSF="}, {"fir": "RPHI MANILA", "hazard": "VA", "qual": "MAYON", "base": 0, "top": 13000, "from": 1784024940, "to": 1784046540, "series": "6", "raw": "WVPH31 RPLL 141029\nRPHI SIGMET 6 VALID 141029/141629 RPLL-\nRPHI MANILA FIR VA ERUPTION MT MAYON PSN N1315 E12341 \nVA CLD OBS AT 0629Z SFC/FL130 MOV SSE="}, {"fir": "ULLL SANKT-PETERBURG", "hazard": "TS", "qual": "FRQ", "base": null, "top": 40000, "from": 1784030400, "to": 1784041200, "series": "5", "raw": "WSRS31 ULLL 141030\nULLL SIGMET 5 VALID 141200/141500 ULLI-\nULLL SANKT-PETERBURG FIR FRQ TS FCST WI N6236 E04318 - N6234 E04611 -\nN6020 E04844 - N6005 E04620 - N5931 E04526 - N5846 E04500 - N5845\nE03830 - N6153 E03856 - N6142 E04211 - N6236 E04318 TOP FL400 STNR\nNC="}, {"fir": "OAKLAND OCEANIC", "hazard": "TS", "qual": "FRQ", "base": null, "top": 45000, "from": 1784025300, "to": 1784039700, "series": "CHARLIE 1", "raw": "WSPN03 KKCI 141035\nSIGP0C\nKZAK SIGMET CHARLIE 1 VALID 141035/141435 KKCI-\nOAKLAND OCEANIC FIR FRQ TS OBS AT 1035Z WI N4508 W17114 - N4349\nW16846 - N3910 W17318 - N4036 W17516 - N4508 W17114. TOP FL450.\nMOV NE 20KT. INTSF."}, {"fir": "WAAF UJUNG PANDANG", "hazard": "VA", "qual": "IBU", "base": 0, "top": 6000, "from": 1784025000, "to": 1784046600, "series": "10", "raw": "WVID21 WAAA 141030\nWAAF SIGMET 10 VALID 141030/141630 WAAA-\nWAAF UJUNG PANDANG  FIR VA\nERUPTION MT IBU PSN N0129 E12738 VA CLD OBS AT 1010Z WI N0127 E12740\n- N0127 E12735 - N0142 E12728 - N0147 E12736 - N0143 E12746 - N0127\nE12740 SFC/FL060 MOV N 05KT NC="}, {"fir": "ZBPE BEIJING", "hazard": "TS", "qual": "EMBD", "base": null, "top": 34000, "from": 1784026500, "to": 1784040900, "series": "2", "raw": "WSCI33 ZBAA 141035\nZBPE SIGMET 2 VALID 141055/141455 ZBAA-\nZBPE BEIJING FIR EMBD TS FCST S OF N44 TOP FL340 MOV E 30KMH NC="}, {"fir": "ULLL SANKT-PETERBURG", "hazard": "TS", "qual": "FRQ", "base": null, "top": 40000, "from": 1784030400, "to": 1784041200, "series": "6", "raw": "WSRS31 ULLL 141036\nULLL SIGMET 6 VALID 141200/141500 ULLI-\nULLL SANKT-PETERBURG FIR FRQ TS FCST WI N6250 E04654 - N6208 E04922 -\nN6103 E04909 - N6042 E05203 - N6131 E05641 - N6110 E05712 - N6042\nE05537 - N6000 E05159 - N6001 E05001 - N6020 E04843 - N6235 E04607 -\nN6250 E04654 TOP FL400 STNR NC="}, {"fir": "VYYF YANGON", "hazard": "TS", "qual": "EMBD", "base": null, "top": 51000, "from": 1784025540, "to": 1784039940, "series": "03", "raw": "WSBM31 VYYY 141039\nVYYF SIGMET 03 VALID 141039/141439 VYYY-\nVYYF YANGON FIR EMBD TS FCST WI N1641 E09630 - N1504 E09808 - N1202 \nE09607 - N1421 E09339 - N1641 E09630 TOP FL510 MOV SW 05KT INTSF="}, {"fir": "VECF KOLKATA", "hazard": "TS", "qual": "EMBD", "base": null, "top": 53000, "from": 1784026800, "to": 1784041200, "series": "3", "raw": "WSIN31 VECC 141040\nVECF SIGMET 3 VALID 141100/141500 VECC- VECF KOLKATA FIR EMBD TS FCST WI N2553 E08719 - N2125 E09010 - N1832 E09200 - N1400 E09200 - N1538 E08608 - N1949 E08226 - N2553 E08719 TOP FL530 MOV SW 15KT NC="}, {"fir": "UCFO OSH", "hazard": "TS", "qual": "EMBD", "base": null, "top": 35000, "from": 1784025780, "to": 1784037600, "series": "2", "raw": "WSKY31 UCFO 141041\nUCFO SIGMET 2 VALID 141043/141400 UCFO-\nUCFO OSH FIR EMBD TS FCST S OF N4036 TOP FL350 MOV NE 20KMH NC="}, {"fir": "VECF KOLKATA", "hazard": "TS", "qual": "EMBD", "base": null, "top": 50000, "from": 1784025780, "to": 1784040000, "series": "A1", "raw": "WSIN31 VECC 141043\nVECF SIGMET A1 VALID 141043/141440 VECC- VECF KOLKATA FIR EMBD TS OBS WI N2711 E09645 - N2211 E09310 - N2205 E09304 - N2532 E08946 - N2656 E08825 - N2804 E09723 - N2711 E09645 TOP FL500 MOV W 15KT NC="}, {"fir": "FSSS SEYCHELLES", "hazard": "TS", "qual": "EMBD", "base": null, "top": 42000, "from": 1784025600, "to": 1784040000, "series": "03", "raw": "WSSC31 FSIA 141034\nFSSS SIGMET 03 VALID 141040/141440 FSIA-\nFSSS SEYCHELLES FIR EMBD TS OBS WI N0304 E05343 - N0542 E06000 - S0700 E06000 - S0357 E05130 - N0304 E05343 TOP ABV FL420 STNR NC="}, {"fir": "UHMM MAGADAN", "hazard": "ICE", "qual": "SEV", "base": 600, "top": 15000, "from": 1784030400, "to": 1784044800, "series": "M04", "raw": "WSRA31 RUMG 141044\nUHMM SIGMET M04 VALID 141200/141600 UHMM-\nUHMM MAGADAN FIR SEV ICE FCST WI N7020 E17100 - N7000 E17600 - N6800\nW17600 - N6704 W17300 - N6700 W16858 - N6500 W16858 - N6403 W17212 -\nN6400 W17500 - N6500 W17600 - N6500 E18000 - N6600 E17900 - N6700\nE17900 - N6730 E17650 - N6730 E17100 - N7020 E17100 FL006/150 STNR\nNC="}, {"fir": "SCIZ ISLA DE PASCUA", "hazard": "TURB", "qual": "SEV", "base": 25000, "top": 40000, "from": 1784026980, "to": 1784041380, "series": "A3", "raw": "WSCH31 SCIP 141045\nSCIZ SIGMET A3 VALID 141103/141503 SCIP-\nSCIZ ISLA DE PASCUA FIR SEV TURB FCST WI S3000 W12800 - S3100 W11400 \n- S2100 W09800 - S2800 W09000 - S4000 W10700 - S3900 W13100 FL250/400\n MOV E NC="}, {"fir": "UWWW SAMARA", "hazard": "TS", "qual": "EMBD", "base": null, "top": 39000, "from": 1784026800, "to": 1784041200, "series": "5", "raw": "WSRS31 UWWW 141047\nUWWW SIGMET 5 VALID 141100/141500 UWWW-\nUWWW SAMARA FIR EMBD TSGR FCST N OF LINE N5252 E05800 - N5102 E05444\n- N5327 E05002 - N5333 E04232 TOP FL390 MOV N 30KMH NC="}, {"fir": "YBBB BRISBANE", "hazard": "TURB", "qual": "SEV", "base": 30000, "top": 40000, "from": 1784026140, "to": 1784040540, "series": "E01", "raw": "WSAU21 YMMC 141049\nYBBB SIGMET E01 VALID 141049/141449 YMMC-\nYBBB BRISBANE FIR SEV TURB FCST WI S1200 E14010 - S1820 E13550 -\nS1540 E12310 - S1610 E10800 - S1200 E10650 - S1200 E12320 FL300/400\nSTNR NC="}, {"fir": "YMMM MELBOURNE", "hazard": "TURB", "qual": "SEV", "base": 30000, "top": 40000, "from": 1784026200, "to": 1784040600, "series": "O01", "raw": "WSAU21 YMMC 141050\nYMMM SIGMET O01 VALID 141050/141450 YMMC-\nYMMM MELBOURNE FIR SEV TURB FCST WI S1200 E14010 - S1820 E13550 -\nS1540 E12310 - S1610 E10800 - S1200 E10650 - S1200 E10700 FL300/400\nSTNR NC="}, {"fir": "VOMF CHENNAI", "hazard": "TS", "qual": "EMBD", "base": null, "top": 41000, "from": 1784026200, "to": 1784040600, "series": "A02", "raw": "WSIN31 VOMM 141040\nVOMF SIGMET A02 VALID 141050/141450 VOMM- VOMF CHENNAI FIR EMBD TS\nFCST WI N1651 E08435 - N1537 E08550 - N1354 E09200 - N1311 E08710 -\nN1538 E08356 - N1651 E08435 TOP FL410 STNR NC="}, {"fir": "GOOO DAKAR OCEANIC", "hazard": "TS", "qual": "EMBD", "base": null, "top": 45000, "from": 1784026800, "to": 1784041200, "series": "A03", "raw": "WSSG31 GOOY 141058\nGOOO SIGMET A03 VALID 141100/141500 GOBD-\nGOOO DAKAR OCEANIC FIR/UIR EMBD TS OBS AT 1050Z\nWI N0544 W01332 - N0636 W02748 - N0957 W02824 - \n   N1202 W02017 - N0544 W01332\n   TOP FL450 MOV W 15KT NC="}, {"fir": "SBCW CURITIBA", "hazard": "TS", "qual": "EMBD", "base": null, "top": 38000, "from": 1784028600, "to": 1784043000, "series": "1", "raw": "WSBZ23 SBGL 141125\nSBCW SIGMET 1 VALID 141130/141530 SBCW - SBCW CURITIBA FIR EMBD TS FCST WI S2243 W04116 - S2400 W04011 - S2226 W03809 - S2159 W03835 - S2243 W04116 TOP FL380 STNR NC="}, {"fir": "OEJD JEDDAH", "hazard": "TS", "qual": "EMBD", "base": null, "top": 39000, "from": 1784026800, "to": 1784041200, "series": "01", "raw": "WSSD20 OEJD 141102\nOEJD SIGMET 01 VALID 141100/141500 OEJN -\nOEJD JEDDAH FIR EMBD TS FCST WI N2107 E04012 - N2121 E04127 - N1724 E04411\nN1624 E04241 - N2107 E04012 TOP ABV FL390 MOV W INTSF="}, {"fir": "NZZC NEW ZEALAND", "hazard": "TURB", "qual": "SEV", "base": 0, "top": 13000, "from": 1784026980, "to": 1784041380, "series": "48", "raw": "WSNZ21 NZKL 141101\nNZZC SIGMET 48 VALID 141103/141503 NZKL-\nNZZC NEW ZEALAND FIR SEV TURB FCST WI S4520 E17000 - S4420 E16830 -\nS4140 E17310 - S4200 E17400 - S4340 E17150 - S4520 E17000 SFC/FL130\nSTNR NC="}, {"fir": "VVHN HANOI", "hazard": "TS", "qual": "EMBD", "base": null, "top": 50000, "from": 1784027100, "to": 1784041500, "series": "1", "raw": "WSVS31 VVGL 141105\nVVHN SIGMET 1 VALID 141105/141505 VVGL-\nVVHN HANOI FIR EMBD TS OBS WI N2128 E10801 - N1845 E10527 - N1915\nE10401 - N2006 E10459 - N2212 E10222 - N2244 E10230 - N2128 E10801\nTOP FL500 STNR NC="}, {"fir": "RJJJ FUKUOKA", "hazard": "TS", "qual": "FRQ", "base": null, "top": 50000, "from": 1784026980, "to": 1784041380, "series": "A04", "raw": "WSJP31 RJTD 141103\nRJJJ SIGMET A04 VALID 141103/141503 RJTD-\nRJJJ FUKUOKA FIR FRQ TS FCST WI N2100 E14400 - N2804 E15310 - N2700\nE15500 - N2435 E15500 - N2100 E15045 - N2100 E14400 TOP FL500 STNR\nNC="}, {"fir": "LTAA ANKARA", "hazard": "TS", "qual": "EMBD", "base": null, "top": 32000, "from": 1784027100, "to": 1784041200, "series": "5", "raw": "WSTU31 LTAA 141105\nLTAA SIGMET 5 VALID 141105/141500 LTAC-\nLTAA ANKARA FIR EMBD TS FCST N OF LINE N4035 E03100 - N4035 E03400 -\nN4035 E03700\n TOP FL320 MOV N 10KT NC="}, {"fir": "WMFC KUALA LUMPUR", "hazard": "TS", "qual": "EMBD", "base": null, "top": null, "from": 1784027700, "to": 1784038500, "series": "9", "raw": "WSMS31 WMKK 141107\nWMFC SIGMET 9 VALID 141115/141415 WMKK-\nWMFC KUALA LUMPUR FIR EMBD TS\nOBS E OF LINE N0700 E09829 - N0503 E09832 AND N OF LINE N0429 E09908\n- N0337 E10142 - N0507 E10335 TOP FL520 MOV SSW 10KT INTSF="}, {"fir": "WMFC KUALA LUMPUR", "hazard": "TS", "qual": "EMBD", "base": null, "top": null, "from": 1784027700, "to": 1784038500, "series": "9", "raw": "WSMS31 WMKK 141107\nWMFC SIGMET 9 VALID 141115/141415 WMKK-\nWMFC KUALA LUMPUR FIR EMBD TS\nOBS E OF LINE N0700 E09829 - N0503 E09832 AND N OF LINE N0429 E09908 - N0337 E10142 - N0507 E10335 TOP FL520 MOV SSW 10KT INTSF="}, {"fir": "SBAZ AMAZONICA", "hazard": "TURB", "qual": "SEV", "base": 33000, "top": 37000, "from": 1784028600, "to": 1784043000, "series": "32", "raw": "WSBZ23 SBGL 141125\nSBAZ SIGMET 32 VALID 141130/141530 SBAZ - SBAZ AMAZONICA FIR SEV TURB FCST WI S0534 W06322 - S0756 W05620 - S1022 W05004 - S1013 W04902 - S0950 W04852 - S0937 W04822 - S0944 W04758 - S1017 W04741 - S1020 W04719 - S0932 W04709 - S0913 W04655 - S0534 W05651 - S0614 W05710 - S0416 W06023 - S0342 W06156 - S0534 W06322 FL330/370 STNR NC="}, {"fir": "SCIZ ISLA DE PASCUA", "hazard": "TS", "qual": "EMBD", "base": null, "top": 28000, "from": 1784028600, "to": 1784043000, "series": "04", "raw": "WSCH31 SCIP 141110\nSCIZ SIGMET 04 VALID 141130/141530 SCIP-\nSCIZ ISLA DE PASCUA FIR EMBD TS FCST WI S3300 W12000 - S3500 W11600 -\n S3600 W11600 - S3500 W12300 TOP FL280 MOV E WKN="}, {"fir": "SBBS BRASILIA", "hazard": "TURB", "qual": "SEV", "base": 33000, "top": 37000, "from": 1784028600, "to": 1784043000, "series": "4", "raw": "WSBZ23 SBGL 141125\nSBBS SIGMET 4 VALID 141130/141530 SBBS - SBBS BRASILIA FIR SEV TURB FCST WI S1022 W05004 - S1134 W04701 - S1020 W04719 - S1017 W04741 - S0944 W04758 - S0937 W04822 - S0950 W04852 - S1013 W04902 - S1022 W05004 FL330/370 STNR NC="}, {"fir": "SBRE RECIFE", "hazard": "TURB", "qual": "SEV", "base": 33000, "top": 37000, "from": 1784028600, "to": 1784043000, "series": "7", "raw": "WSBZ23 SBGL 141125\nSBRE SIGMET 7 VALID 141130/141530 SBRE - SBRE RECIFE FIR SEV TURB FCST WI S1020 W04719 - S1134 W04701 - S1153 W04611 - S0930 W04608 - S0913 W04655 - S0932 W04709 - S1020 W04719 FL330/370 STNR NC="}, {"fir": "SBAO ATLANTICO", "hazard": "TURB", "qual": "SEV", "base": 29000, "top": 38000, "from": 1784028600, "to": 1784043000, "series": "18", "raw": "WSBZ23 SBGL 141125\nSBAO SIGMET 18 VALID 141130/141530 SBAO - SBAO ATLANTICO FIR SEV TURB FCST WI S2734 W02345 - S3447 W01744 - S3402 W01116 - S3314 W01153 - S2301 W02320 - S2258 W02324 - S2548 W02145 - S2909 W01735 - S3123 W01833 - S2734 W02345 FL290/380 STNR NC="}, {"fir": "SBAO ATLANTICO", "hazard": "ICE", "qual": "SEV", "base": 10000, "top": 14000, "from": 1784028600, "to": 1784043000, "series": "19", "raw": "WSBZ23 SBGL 141125\nSBAO SIGMET 19 VALID 141130/141530 SBAO - SBAO ATLANTICO FIR SEV ICE FCST WI S3157 W03029 - S3456 W02702 - S3523 W02655 - S3523 W02209 - S3509 W01930 - S3128 W02658 - S3157 W03029 FL100/140 MOV E 10KT NC="}, {"fir": "SCTZ PUERTO MONTT", "hazard": "TURB", "qual": "SEV", "base": 20000, "top": 35000, "from": 1784030400, "to": 1784044800, "series": "A4", "raw": "WSCH31 SCTE 141111\nSCTZ SIGMET A4 VALID 141200/141600 SCTE-\nSCTZ PUERTO MONTT FIR SEV TURB FCST WI S3830 W08000 - S3930 W07130 - \nS4400 W07130 - S4000 W08000 FL200/350 MOV NE NC="}, {"fir": "YBBB BRISBANE", "hazard": "TURB", "qual": "SEV", "base": 20000, "top": 40000, "from": 1784028060, "to": 1784042460, "series": "C02", "raw": "WSAU21 YMMC 141114\nYBBB SIGMET C02 VALID 141121/141521 YMMC-\nYBBB BRISBANE FIR SEV TURB FCST WI S5000 E14510 - S4310 E14520 -\nS3120 E14020 - S3150 E14610 - S4250 E15530 - S5000 E15600 FL200/400\nMOV ENE 45KT NC="}, {"fir": "YMMM MELBOURNE", "hazard": "TURB", "qual": "SEV", "base": 20000, "top": 40000, "from": 1784028060, "to": 1784042460, "series": "C05", "raw": "WSAU21 YMMC 141114\nYMMM SIGMET C05 VALID 141121/141521 YMMC-\nYMMM MELBOURNE FIR SEV TURB FCST WI S5000 E14510 - S4310 E14520 -\nS3120 E14020 - S3150 E14610 - S4250 E15530 - S5000 E15600 FL200/400\nMOV ENE 45KT NC="}, {"fir": "SBAZ AMAZONICA", "hazard": "TS", "qual": "EMBD", "base": null, "top": 39000, "from": 1784028600, "to": 1784043000, "series": "34", "raw": "WSBZ23 SBGL 141125\nSBAZ SIGMET 34 VALID 141130/141530 SBAZ - SBAZ AMAZONICA FIR EMBD TS FCST WI N0056 W06551 - S0222 W06343 - S0111 W06023 - S0058 W05750 - N0055 W05758 - N0229 W06358 - N0207 W06349 - N0114 W06458 - N0056 W06551 TOP FL390 STNR NC="}, {"fir": "SBAZ AMAZONICA", "hazard": "TS", "qual": "EMBD", "base": null, "top": 39000, "from": 1784028600, "to": 1784043000, "series": "33", "raw": "WSBZ23 SBGL 141125\nSBAZ SIGMET 33 VALID 141130/141530 SBAZ - SBAZ AMAZONICA FIR EMBD TS FCST WI S0331 W06137 - S0614 W05710 - S0408 W05610 - S0201 W06004 - S0331 W06137 TOP FL390 STNR NC="}, {"fir": "SBAZ AMAZONICA", "hazard": "TS", "qual": "EMBD", "base": null, "top": 39000, "from": 1784028600, "to": 1784043000, "series": "35", "raw": "WSBZ23 SBGL 141125\nSBAZ SIGMET 35 VALID 141130/141530 SBAZ - SBAZ AMAZONICA FIR EMBD TS FCST WI N0150 W06931 - S0047 W06658 - N0019 W06528 - N0055 W06551 - N0046 W06618 - N0215 W06723 - N0150 W06931 TOP FL390 STNR NC="}, {"fir": "SBAZ AMAZONICA", "hazard": "TS", "qual": "EMBD", "base": null, "top": 39000, "from": 1784028600, "to": 1784043000, "series": "36", "raw": "WSBZ23 SBGL 141125\nSBAZ SIGMET 36 VALID 141130/141530 SBAZ - SBAZ AMAZONICA FIR EMBD TS FCST WI S0354 W05635 - S0408 W05610 - S0450 W05630 - S0532 W05538 - S0722 W04939 - S0421 W04820 - S0220 W05546 - S0354 W05635 TOP FL390 STNR NC="}, {"fir": "MMFR MEXICO", "hazard": "VA", "qual": "POPOCATEPETL", "base": 0, "top": 24000, "from": 1784027580, "to": 1784049180, "series": "2", "raw": "WVMX31 MMMX 141246\nMMEX SIGMET 2 VALID 141113/141713 MMMX-\nMMFR MEXICO FIR VA POPOCATEPETL PSN N1901 W09837 OBS\n AT 141113Z\nVA CLD BTN SFC/FL240 WI N1902W09837 N1900W09837 N1837W09931 N1902W099\n37\n         N1902W09837\nMOV W 20KT NC.\nOUTLK 14/1713Z VA CLD BTN SFC/FL240 WI N1902W09837 N1900W09837 N1837W\n09931 N1902W09937\n         N1902W09837\nAFFECTED AIRWAYS ARRIVALS LARLO 4A AND ESPOS 3A AND DEPARTURES TEVOS \n2A.\n        ="}, {"fir": "SBAO ATLANTICO", "hazard": "TS", "qual": "EMBD", "base": null, "top": 39000, "from": 1784028600, "to": 1784043000, "series": "20", "raw": "WSBZ23 SBGL 141125\nSBAO SIGMET 20 VALID 141130/141530 SBAO - SBAO ATLANTICO FIR EMBD TS FCST WI S2649 W02447 - S3123 W01833 - S2909 W01735 - S2548 W02145 - S2238 W02336 - S2339 W02601 - S2649 W02447 TOP FL390 STNR NC="}, {"fir": "FCCC BRAZZAVILLE", "hazard": "TS", "qual": "EMBD", "base": null, "top": 43000, "from": 1784030700, "to": 1784045100, "series": "A3", "raw": "WSCG31 FCBB 141120\nFCCC SIGMET A3 VALID 141205/141605 FCBB-\nFCCC BRAZZAVILLE FIR/UIR EMBD TS OBS AT 1115Z\nE OF LINE N0800 E01500 - N0418 E01500\nTOP FL430 MOV W 05KT INTSF="}, {"fir": "RPHI MANILA", "hazard": "TS", "qual": "EMBD", "base": null, "top": 53000, "from": 1784028600, "to": 1784043000, "series": "A03", "raw": "WSPH31 RPLL 141125\nRPHI SIGMET A03 VALID 141130/141530 RPLL-\nRPHI MANILA FIR EMBD TS OBS WI \nN1826 E12019 - N1256 E11800 - N1109 E11400 - \nN1640 E11400 - N2100 E11730 - N1826 E12019 \nTOP FL530 STNR NC="}, {"fir": "MMFR MEXICO", "hazard": "TS", "qual": "EMBD", "base": null, "top": 45000, "from": 1784028480, "to": 1784042880, "series": "K2", "raw": "WSMX31 MMMX 141130\nMMEX SIGMET K2 VALID 141128/141528 MMMX-\nMMFR MEXICO FIR EMBD TS OBS\n AT 1128Z\nWI N1849W09616 - N1911W09522 - N2012W09433 - N1942W09353 - N1822W09412\n         - N1812W09458 - N1708W09510 - N1711W09550 - N1849W09616 CB TOP ABV FL450\n        \nMOV NW 08KT  NC.\n="}, {"fir": "ZPKM KUNMING", "hazard": "TS", "qual": "EMBD", "base": null, "top": 48000, "from": 1784030400, "to": 1784044800, "series": "2", "raw": "WSCI36 ZUUU 141129\nZPKM SIGMET 2 VALID 141200/141600 ZUUU- ZPKM KUNMING FIR EMBD TS\n FCST WI N3134 E09826-N3324 E10354-N2902 E10506-N2817 E08954-N3102\n E08431-N3314 E08717-N3134 E09826 TOP FL480 STNR NC="}, {"fir": "MMFR MEXICO", "hazard": "TS", "qual": "OCNL", "base": null, "top": 49000, "from": 1784028720, "to": 1784043120, "series": "G3", "raw": "WSMX31 MMMX 141134\nMMEX SIGMET G3 VALID 141132/141532 MMMX-\nMMFR MEXICO FIR OCNL TS OBS\n AT 1132Z\nWI N1752W10250 - N1750W10209 - N1541W09848 - N1431W09807 - N1401W09908\n         - N1424W10050 - N1525W10212 - N1625W10216 - N1752W10250 CB TOP FL490\nMOV WNW 08KT  NC.\n="}, {"fir": "MHCC CENTRAL AMERICAN", "hazard": "TS", "qual": "EMBD", "base": null, "top": 50000, "from": 1784028900, "to": 1784043300, "series": "J4", "raw": "WSHO31 MHTG 141135\nMHTG SIGMET J4 VALID 141135/141535 MHTG-\nMHCC CENTRAL AMERICAN FIR EMBD TS OBS AT 1130Z \nWI N1123 W09615 - N1233 W09520 - N1202 W09254 - \nN0952 W09335 TOP FL500 MOV SW 10K WKN="}, {"fir": "YBBB BRISBANE", "hazard": "TURB", "qual": "SEV", "base": 23000, "top": 35000, "from": 1784031360, "to": 1784045760, "series": "A04", "raw": "WSAU21 YMMC 141136\nYBBB SIGMET A04 VALID 141216/141616 YMMC-\nYBBB BRISBANE FIR SEV TURB FCST WI S2816 E11536 - S2446 E11554 -\nS2610 E12350 - S2210 E14050 - S2400 E14830 - S2930 E13700 - S3210\nE12150 FL230/350 MOV E 15KT NC="}, {"fir": "YMMM MELBOURNE", "hazard": "TURB", "qual": "SEV", "base": 23000, "top": 35000, "from": 1784031360, "to": 1784045760, "series": "J11", "raw": "WSAU21 YMMC 141136\nYMMM SIGMET J11 VALID 141216/141616 YMMC-\nYMMM MELBOURNE FIR SEV TURB FCST WI S2816 E11536 - S2446 E11554 -\nS2610 E12350 - S2210 E14050 - S2400 E14830 - S2930 E13700 - S3210\nE12150 FL230/350 MOV E 15KT NC="}, {"fir": "MMFO MAZATLAN OCEANICA", "hazard": "TS", "qual": "OCNL", "base": null, "top": 50000, "from": 1784028960, "to": 1784043360, "series": "C3", "raw": "WSMX31 MMMX 141137\nMMID SIGMET C3 VALID 141136/141536 MMMX-\nMMFO MAZATLAN OCEANICA FIR OCNL TS OBS\n AT 1136Z\nWI N1130W10552 - N1209W10421 - N1313W10303 - N1551W10605 - N1800W10749\n         - N1703W10918 - N1452W10851 - N1309W10758 - N1130W10552 CB TOP FL500\nMOV W 08KT  INTSF.\n="}, {"fir": "WAAF UJUNG PANDANG", "hazard": "VA", "qual": "SEMERU", "base": 0, "top": 16000, "from": 1784028960, "to": 1784050200, "series": "11", "raw": "WVID21 WAAA 141136\nWAAF SIGMET 11 VALID 141136/141730 WAAA-\nWAAF UJUNG PANDANG  FIR VA\nERUPTION MT SEMERU PSN S0806 E11255 VA CLD OBS AT 1110Z WI S0802\nE11255 - S0809 E11326 - S0847 E11328 - S0847 E11312 - S0809 E11250 -\nS0802 E11255 SFC/FL160 MOV SE 10KT INTSF="}, {"fir": "MMFR MEXICO", "hazard": "TS", "qual": "OCNL", "base": null, "top": 50000, "from": 1784029140, "to": 1784043540, "series": "R3", "raw": "WSMX31 MMMX 141140\nMMEX SIGMET R3 VALID 141139/141539 MMMX-\nMMFR MEXICO FIR OCNL TS OBS\n AT 1139Z\nWI N1824W10751 - N1908W10533 - N1808W10412 - N1539W10256 - N1355W10320\n         - N1459W10500 - N1643W10603 - N1728W10709 - N1824W10751 CB TOP FL500\nMOV WNW 08KT  INTSF.\n="}, {"fir": "VOMF CHENNAI", "hazard": "TS", "qual": "EMBD", "base": null, "top": 46000, "from": 1784029500, "to": 1784043900, "series": "B01", "raw": "WSIN31 VOMM 141135\nVOMF SIGMET B01 VALID 141145/141545 VOMM- VOMF CHENNAI FIR EMBD TS\nFCST WI N0750 E09238 - N0819 E09122 - N1005 E09235 - N0922 E09355 -\nN0750 E09238 TOP FL460 STNR NC="}, {"fir": "YMMM MELBOURNE", "hazard": "TURB", "qual": "SEV", "base": 0, "top": 6000, "from": 1784034000, "to": 1784037600, "series": "P01", "raw": "WSAU21 YMRF 141142\nYMMM SIGMET P01 VALID 141300/141400 YMRF-\nYMMM MELBOURNE FIR SEV TURB FCST WI S4210 E14640 - S4300 E14730 -\nS4340 E14700 - S4340 E14640 - S4210 E14610 SFC/6000FT STNR NC="}, {"fir": "UMMV MINSK", "hazard": "TS", "qual": "EMBD", "base": null, "top": 39000, "from": 1784029380, "to": 1784041200, "series": "1", "raw": "WSBY31 UMMS 141143\nUMMV SIGMET 1 VALID 141143/141500 UMMS-\nUMMV MINSK FIR EMBD TSGR FCST ENTIRE FIR TOP FL390 MOV SW 40KMH NC="}, {"fir": "YMMM MELBOURNE", "hazard": "TURB", "qual": "SEV", "base": 0, "top": 7000, "from": 1784030400, "to": 1784044800, "series": "L02", "raw": "WSAU21 YBRF 141144\nYMMM SIGMET L02 VALID 141200/141600 YBRF-\nYMMM MELBOURNE FIR SEV TURB FCST WI S3530 E14930 - S3610 E15010 -\nS3740 E15010 - S3700 E14840 SFC/7000FT STNR NC="}, {"fir": "MMFO MAZATLAN OCEANICA", "hazard": "TS", "qual": "OCNL", "base": null, "top": 50000, "from": 1784029380, "to": 1784043780, "series": "L1", "raw": "WSMX31 MMMX 141144\nMMID SIGMET L1 VALID 141143/141543 MMMX-\nMMFO MAZATLAN OCEANICA FIR OCNL TS OBS\n AT 1143Z\nWI N0839W10902 - N1000W10901 - N1007W10759 - N1041W10635 - N0933W10606\n         - N0839W10902 CB TOP FL500\nMOV W 08KT  INTSF.\n="}, {"fir": "VTBB BANGKOK", "hazard": "TS", "qual": "EMBD", "base": null, "top": 53000, "from": 1784029800, "to": 1784044200, "series": "02", "raw": "WSTH31 VTBS 141150\nVTBB SIGMET 02 VALID 141150/141550 VTBS-\nVTBB BANGKOK FIR EMBD TS OBS WI N1431 E10258 - N1632 E09855 - N1721\nE09949 - N1643 E10443 - N1513 E10531 - N1431 E10258 TOP FL530 MOV\nWSW 05KT NC="}, {"fir": "YBBB BRISBANE", "hazard": "TURB", "qual": "SEV", "base": 0, "top": 7000, "from": 1784030400, "to": 1784037600, "series": "F01", "raw": "WSAU21 YBRF 141147\nYBBB SIGMET F01 VALID 141200/141400 YBRF-\nYBBB BRISBANE FIR SEV TURB FCST WI S3330 E15010 - S3330 E15050 -\nS3420 E15050 - S3420 E15020 SFC/7000FT STNR NC="}, {"fir": "YMMM MELBOURNE", "hazard": "TURB", "qual": "SEV", "base": 0, "top": 7000, "from": 1784030400, "to": 1784037600, "series": "M02", "raw": "WSAU21 YBRF 141147\nYMMM SIGMET M02 VALID 141200/141400 YBRF-\nYMMM MELBOURNE FIR SEV TURB FCST WI S3330 E15010 - S3330 E15050 -\nS3420 E15050 - S3420 E15020 SFC/7000FT STNR NC="}, {"fir": "VGFR DHAKA", "hazard": "TS", "qual": "EMBD", "base": null, "top": 48000, "from": 1784030400, "to": 1784044800, "series": "04", "raw": "WSBW20 VGHS 141100\nVGFR SIGMET 04 VALID 141200/141600 VGHS-\nVGFR DHAKA FIR EMBD TS FCST ENTIRE FIR TOP FL480 MOV NNW 10KT NC="}, {"fir": "MHCC CENTRAL AMERICAN", "hazard": "TS", "qual": "EMBD", "base": null, "top": 50000, "from": 1784029800, "to": 1784044200, "series": "C2", "raw": "WSCA31 MHTG 141150\nMHTG SIGMET C2 VALID 141150/141550 MHTG-\nMHCC CENTRAL AMERICAN FIR EMBD TS OBS AT 1145Z\nWI N1118 W08429 - N1533 W08432 - N1559 W08726 -\nN1651 W08707 - N1619 W08221 - N1500 W08220\n- N1253 W08253 - N1055 W08252 TOP FL500 MOV NW 05KT INTSF="}, {"fir": "LRBB BUCURESTI", "hazard": "TS", "qual": "EMBD", "base": null, "top": 37000, "from": 1784030400, "to": 1784037600, "series": "T03", "raw": "WSRO31 LROM 141151\nLRBB SIGMET T03 VALID 141200/141400 LROM-\nLRBB BUCURESTI FIR\nEMBD TS OBS WI N4500 E02650 - N4635 E02520 - N4630 E02615 - N4550\nE02715 - N4500 E02650 TOP FL370 MOV S 10KT NC="}, {"fir": "YMMM MELBOURNE", "hazard": "TURB", "qual": "SEV", "base": 12000, "top": 30000, "from": 1784032200, "to": 1784046600, "series": "I11", "raw": "WSAU21 YMMC 141155\nYMMM SIGMET I11 VALID 141230/141630 YMMC-\nYMMM MELBOURNE FIR SEV TURB FCST WI S3155 E09310 - S4750 E10630 -\nS4900 E11610 - S4950 E11900 - S5000 E09830 - S3350 E08750 FL120/300\nMOV E 35KT NC="}, {"fir": "SAVF COMODORO RIVADAVIA", "hazard": "ICE", "qual": "SEV", "base": 6000, "top": 22000, "from": 1784030220, "to": 1784041020, "series": "C1", "raw": "WSAG31 SABE 141157\nSAVF SIGMET C1 VALID 141157/141457 SABE-\nSAVF COMODORO RIVADAVIA FIR SEV ICE FCST AT 1157Z\nWI S4118 W07151 - S4205 W07154 - S4224 W07040 - S4420 W06854 - S4420\nW06457 - S4204 W06526 - S4120 W05941 - S4004 W06148 - S4049 W06529 - \nS4115 W07021 - S4104 W07103 - S4118 W07151 FL060/220 STNR NC="}, {"fir": "ANTANANARIVO", "hazard": "TS", "qual": "EMBD", "base": null, "top": 36000, "from": 1784030400, "to": 1784044800, "series": "C4", "raw": "WSMG31 FMMI 141200\nFMMM SIGMET C4 VALID 141200/141600 FMMI-\nANTANANARIVO FIR/UIR EMBD TS OBS WI S2730 E04000 - S2540 E05136 -\nS2718 E05700 - S3000 E05700 - S3000 E04000 TOP ABV FL360 STNR NC="}, {"fir": "OPLR LAHORE", "hazard": "TS", "qual": "EMBD", "base": null, "top": null, "from": 1784032200, "to": 1784046600, "series": "04", "raw": "WSPK31 OPLA 141200\nOPLR SIGMET 04 VALID 141230/141630 OPLA-\nOPLR LAHORE FIR EMBD TS  OBS N OF N30 MOV SE NC="}, {"fir": "ZWUQ URUMQI", "hazard": "TS", "qual": "EMBD", "base": null, "top": 34000, "from": 1784030400, "to": 1784044800, "series": "6", "raw": "WSCI39 ZWWW 141200\nZWUQ SIGMET 6 VALID 141200/141600 ZWWW - \nZWUQ URUMQI FIR EMBD TS FCST WI \nN3959 E07356 - N4107 E07740 - N3948 E07833 - \nN3829 E07417 - N3959 E07356\nTOP FL340 MOV E 25KMH NC="}, {"fir": "SBAO ATLANTICO", "hazard": "TS", "qual": "EMBD", "base": null, "top": 39000, "from": 1784028600, "to": 1784043000, "series": "26", "raw": "WSBZ23 SBGL 141125\nSBAO SIGMET 26 VALID 141130/141530 SBAO - SBAO ATLANTICO FIR EMBD TS FCST WI S2400 W04011 - S2913 W03629 - S2839 W03358 - S2250 W03352 - S2157 W03827 - S2159 W03835 - S2226 W03809 - S2400 W04011 TOP FL390 STNR NC="}, {"fir": "UHMM MAGADAN", "hazard": "VA", "qual": "SHEVELUCH", "base": 0, "top": 39000, "from": 1784031000, "to": 1784049600, "series": "P04", "raw": "WVRA31 RUPK 141209\nUHMM SIGMET P04 VALID 141210/141720 UHPP-\nUHMM MAGADAN FIR VA ERUPTION MT SHEVELUCH PSN N5638 E16119 VA CLD OBS\nAT 1120Z WI N5422 E16550 - N5414 E16656 - N5349 E16654 - N5359 E16539\n- N5422 E16550 SFC/FL390 MOV SE 80KMH FCST AT 1720Z NO VA EXP="}, {"fir": "SOOO CAYENNE", "hazard": "ICE", "qual": "SEV", "base": 17500, "top": 19000, "from": 1784030700, "to": 1784038200, "series": "06", "raw": "WSFG20 TFFF 141209\nSOOO SIGMET 06 VALID 141205/141410 TFFF-\nSOOO CAYENNE FIR/UIR SEV ICE OBS WI N0545 W03945 - N0715 W04500 -\nN1000 W04615 - N1015 W04230 - N0815 W04045 - N1030 W03715 - N0745\nW03515 - N0545 W03945 FL175/190 STNR NC="}, {"fir": "UCFO OSH", "hazard": "TS", "qual": "EMBD", "base": null, "top": 28000, "from": 1784031120, "to": 1784044800, "series": "3", "raw": "WSKY31 UCFO 141210\nUCFO SIGMET 3 VALID 141212/141600 UCFO-\nUCFO OSH FIR EMBD TS FCST N4127 E07312 TOP FL280 MOV NE 20KMH NC="}, {"fir": "ZLHW LANZHOU", "hazard": "TS", "qual": "EMBD", "base": null, "top": 33000, "from": 1784031600, "to": 1784046000, "series": "3", "raw": "WSCI37 ZLXY 141212\nZLHW SIGMET 3 VALID 141220/141620 ZLXY-\nZLHW LANZHOU FIR EMBD TS FCST E OF LINE N33 E105 - N36 E110 TOP\n FL330 MOV E 30KMH WKN="}, {"fir": "NEW YORK OCEANIC", "hazard": "TS", "qual": "FRQ", "base": null, "top": 45000, "from": 1784031300, "to": 1784045700, "series": "LIMA 3", "raw": "WSNT12 KKCI 141215\nSIGA0L\nKZWY SIGMET LIMA 3 VALID 141215/141615 KKCI-\nNEW YORK OCEANIC FIR FRQ TS OBS AT 1215Z WI N3303 W06719 - N3151\nW05857 - N2909 W06239 - N3046 W06705 - N3303 W06719. TOP FL450.\nMOV ESE 15KT. WKN."}, {"fir": "NEW YORK OCEANIC", "hazard": "TS", "qual": "FRQ", "base": null, "top": 43000, "from": 1784031300, "to": 1784045700, "series": "MIKE 1", "raw": "WSNT13 KKCI 141215\nSIGA0M\nKZWY SIGMET MIKE 1 VALID 141215/141615 KKCI-\nNEW YORK OCEANIC FIR FRQ TS OBS AT 1215Z WI N2740 W05310 - N2429\nW05635 - N2549 W06516 - N2728 W06229 - N2740 W05310. TOP FL430.\nSTNR. INTSF."}, {"fir": "USSV YEKATERINBURG", "hazard": "TS", "qual": "EMBD", "base": null, "top": 39000, "from": 1784034000, "to": 1784048400, "series": "3", "raw": "WSRA31 RUEK 141212\nUSSV SIGMET 3 VALID 141300/141700 USSS-\nUSSV YEKATERINBURG FIR EMBD TSGR FCST S OF LINE N5929 E04529 - N5841\nE06150 - N5420 E06419 TOP FL390 MOV NE 20KMH NC="}, {"fir": "WAAF UJUNG PANDANG", "hazard": "VA", "qual": "DUKONO", "base": 0, "top": 7000, "from": 1784031600, "to": 1784053200, "series": "12", "raw": "WVID21 WAAA 141220\nWAAF SIGMET 12 VALID 141220/141820 WAAA- WAAF UJUNG PANDANG FIR VA\nERUPTION MT DUKONO PSN N0142 E12754 VA CLD OBS AT 1200Z WI N0138\nE12759 - N0138 E12748 - N0237 E12728 - N0258 E12744 - N0246 E12802 -\nN0138 E12759 SFC/FL070 MOV N 05KT NC="}, {"fir": "ZGZU GUANGZHOU", "hazard": "TS", "qual": "EMBD", "base": null, "top": 50000, "from": 1784033400, "to": 1784047800, "series": "4", "raw": "WSCI35 ZGGG 141220\nZGZU SIGMET 4 VALID 141250/141650 ZGGG-\nZGZU GUANGZHOU FIR EMBD TS FCST N OF N2035 AND S OF N2757 TOP FL500\n MOV W 30KMH NC="}, {"fir": "ZHWH WUHAN", "hazard": "TS", "qual": "EMBD", "base": null, "top": 40000, "from": 1784034000, "to": 1784048400, "series": "4", "raw": "WSCI45 ZHHH 141221\nZHWH SIGMET 4 VALID 141300/141700 ZHHH-\nZHWH WUHAN FIR EMBD TS FCST N OF N29 TOP FL400 MOV E 30KMH NC="}, {"fir": "PAZA ANCHORAGE", "hazard": "VA", "qual": "SHEVELUCH", "base": 0, "top": 40000, "from": 1784031540, "to": 1784053020, "series": "INDIA 3", "raw": "WVAK01 PAWU 141224\nWSVAK1\nANCI WS 141219\nPAZA SIGMET INDIA 3 VALID 141219/141817 PANC-\nPAZA ANCHORAGE FIR ANCHORAGE OCEANIC FIR VA ERUPTION MT SHEVELUCH PSN N5639 E16122\nVA CLD OBS AT 1219Z WI N5423 E16552 - N5415 E16659 - N5349 E16654 -\nN5359 E16540 - N5422 E16551 - N5423 E16552 SFC/FL400 MOV SE 40KT NC\nFCST AT 1817Z WI N5225 E17119 - N5233 E17410 - N5141 E17208 - N5145\nE17002 - N5225 E17118 - N5225 E17119 SFC/FL400=\n\nCC JUL 2026 AAWU"}, {"fir": "CZUL MONTREAL", "hazard": "TS", "qual": "FRQ", "base": null, "top": 43000, "from": 1784032200, "to": 1784046600, "series": "C4", "raw": "WSCN05 CWAO 141232\nCZUL SIGMET C4 VALID 141230/141630 CWUL-\nCZUL MONTREAL FIR FRQ TS OBS WI 90NM WID LINE BTN N4938 W07901 - N4844 W07425\nTOP FL430 MOV SE 55KT NC="}, {"fir": "OOMM MUSCAT", "hazard": "TS", "qual": "EMBD", "base": null, "top": 36000, "from": 1784034000, "to": 1784041200, "series": "A2", "raw": "WSOM31 OOMS 141245\nOOMM SIGMET A2 VALID 141300/141500 OOMS-\nOOMM MUSCAT FIR\nEMBD TS OBS WI N2300 E05901 - N2236 E05839 - N2321 E05638 - N2346\nE05658 - N2300 E05901\nTOP ABV FL360 STNR WKN="}, {"fir": "VHHK HONG KONG", "hazard": "TS", "qual": "EMBD", "base": null, "top": 53000, "from": 1784032800, "to": 1784047200, "series": "4", "raw": "WSSS20 VHHH 141235\nVHHK SIGMET 4 VALID 141240/141640 VHHH-\nVHHK HONG KONG FIR\nEMBD TS FCST WI N2100 E11730 - N1642 E11400 - N1930 E11130 - \nN2130 E11130 - N2331 E11620 - N2211 E11730 - N2100 E11730 TOP \nFL530 STNR NC="}, {"fir": "UUWV MOSCOW", "hazard": "TS", "qual": "EMBD", "base": null, "top": 39000, "from": 1784034000, "to": 1784041200, "series": "2", "raw": "WSRS31 UUWV 141234\nUUWV SIGMET 2 VALID 141300/141500 UUWV-\nUUWV MOSCOW FIR EMBD TSGR FCST ENTIRE FIR TOP FL390 MOV SE 20KMH NC="}, {"fir": "ZJSA SANYA", "hazard": "TS", "qual": "EMBD", "base": null, "top": 50000, "from": 1784033400, "to": 1784047800, "series": "4", "raw": "WSCI35 ZJHK 141241\nZJSA SIGMET 4 VALID 141250/141650 ZJHK-\nZJSA SANYA FIR EMBD TS FCST WI N1657 E11344 - N1801 E11247 - N1655\nE11131 - N1555 E11307 - N1657 E11344 TOP FL500 MOV NE 20KMH NC="}, {"fir": "WIIF JAKARTA", "hazard": "TURB", "qual": "SEV", "base": 37000, "top": 45000, "from": 1784033100, "to": 1784043900, "series": "04", "raw": "WSID20 WIII 141242\nWIIF SIGMET 04 VALID 141245/141545 WIII- WIIF JAKARTA FIR SEV TURB\nFCST WI S1034 E10916 - S1200 E11002 - S1200 E11430 - S1023 E11241 -\nS1034 E10916 FL370/450 STNR NC="}, {"fir": "RKRR INCHEON", "hazard": "TURB", "qual": "SEV", "base": 23000, "top": 33000, "from": 1784034000, "to": 1784047440, "series": "X02", "raw": "WSKO31 RKSI 141250\nRKRR SIGMET X02 VALID 141300/141644 RKSI-\nRKRR INCHEON FIR SEV TURB FCST N3741 E12502 - N3423 E12508 -\n       N3610 E12828 - N3835 E13008 - N3838 E12811 - N3817\n       E12704 - N3741 E12502 FL230/330 MOV ENE 30KT INTSF="}, {"fir": "OIIX TEHRAN", "hazard": "TS", "qual": "EMBD", "base": null, "top": 32000, "from": 1784033100, "to": 1784039400, "series": "01", "raw": "WSIR31 OIII 141246\nOIIX SIGMET 01 VALID 141245/141430 OIII-\nOIIX TEHRAN FIR\nEMBD TS OBS/FCST WI N2715 E05704 - N2704 E05939 - N2524 E05933 -\nN2540 E05710 - N2657 E05649 - N2715 E05704 TOP FL320 MOV ENE NC="}, {"fir": "UACN ASTANA", "hazard": "TS", "qual": "EMBD", "base": null, "top": 39000, "from": 1784035800, "to": 1784050200, "series": "4", "raw": "WSKZ31 UACC 141249\nUACN SIGMET 4 VALID 141330/141730 UACC-\nUACN ASTANA FIR EMBD TS FCST N OF N4750 TOP FL390 MOV ESE 20KMH NC="}, {"fir": "SAMF MENDOZA", "hazard": "TURB", "qual": "SEV", "base": 13000, "top": 38000, "from": 1784033640, "to": 1784048040, "series": "1", "raw": "WSAG31 SAME 141254\nSAMF SIGMET 1 VALID 141254/141654 SAME-\nSAMF MENDOZA FIR SEV TURB FCST AT 1254Z\nWI S2901 W06930 - S2946 W06935 - S3011 W06935 - S3104 W07002 - S3125\nW07007 - S3201 W06952 - S3253 W06934 - S3311 W06934 - S3333 W06934 - \nS3402 W06930 - S3403 W06952 - S3503 W07010 - S3531 W07010 - S3610 \nW07017 - S3619 W06857 - S3237 W06828 - S2949 W06828 - S2901 W06930 \nFL130/380 STNR NC="}, {"fir": "RKRR INCHEON", "hazard": "ICE", "qual": "SEV", "base": 22000, "top": 27000, "from": 1784034000, "to": 1784048400, "series": "Y03", "raw": "WSKO31 RKSI 141255\nRKRR SIGMET Y03 VALID 141300/141700 RKSI-\nRKRR INCHEON FIR SEV ICE FCST N3800 E12443 - N3506 E12527 -\n       N3736 E13029 - N3836 E13036 - N3837 E12816 - N3811\n       E12650 - N3800 E12443 FL220/270 MOV ENE 30KT INTSF="}, {"fir": "LIMM MILANO", "hazard": "TS", "qual": "FRQ", "base": null, "top": 42000, "from": 1784034000, "to": 1784041200, "series": "2", "raw": "WSIY31 LIMM 141258\nLIMM SIGMET 2 VALID 141300/141500 LIIB-\nLIMM MILANO FIR FRQ TS OBS WI N4657 E01130 - N4612 E01103 - N4556\nE01252 - N4632 E01343 - N4642 E01223 - N4708 E01203 - N4657 E01130\nTOP FL420 STNR NC="}, {"fir": "LOVV WIEN", "hazard": "TS", "qual": "FRQ", "base": null, "top": 42000, "from": 1784034000, "to": 1784041200, "series": "T04", "raw": "WSOS31 LOWW 141251\nLOVV SIGMET T04 VALID 141300/141500 LOWW-\nLOVV WIEN FIR FRQ TSGR OBS WI N4750 E01541 - N4735 E01550 - N4653\nE01453 - N4632 E01332 - N4637 E01301 - N4746 E01413 - N4741 E01500 -\nN4750 E01541 TOP FL420 NC FCST AT 1500Z WI N4809 E01551 - N4745\nE01615 - N4658 E01613 - N4650 E01600 - N4640 E01602 - N4640 E01500 -\nN4629 E01448 - N4628 E01426 - N4640 E01430 - N4709 E01536 - N4748\nE01510 - N4809 E01551="}, {"fir": "MHCC CENTRAL AMERICAN", "hazard": "VA", "qual": "FUEGO", "base": 0, "top": 14000, "from": 1784034000, "to": 1784055600, "series": "A3", "raw": "WVHO31 MHTG 141300\nMHTG SIGMET A3 VALID 141300/141900 MHTG-\nMHCC CENTRAL AMERICAN FIR VA FUEGO PSN N1428 W09052\nVA CLD OBS AT 1230Z SFC/FL140 N1432 W09110 - N1429 W09052\n- N1428 W09052 - N1425 W09110 - N1432 W09110 MOV W 25KT\nFCST 1830Z VA CLD SFC/FL140 N1434 W09111\n- N1430 W09052 - N1428 W09052 - N1425 W09111 - N1434 W09111="}, {"fir": "OAKLAND OCEANIC", "hazard": "TS", "qual": "EMBD", "base": null, "top": 57000, "from": 1784034000, "to": 1784048400, "series": "VICTOR 4", "raw": "WSPA09 PHFO 141303\nSIGPAV\n\nKZAK SIGMET VICTOR 4 VALID 141300/141700 PHFO-\nOAKLAND OCEANIC FIR EMBD TS OBS AT 1300Z WI N2100 E14530 - N2100\nE15145 - N2000 E15130 - N1630 E14845 - N1545 E14100 - N2100 E14530.\nTOP FL570. MOV E 5KT. NC."}, {"fir": "OAKLAND OCEANIC", "hazard": "TS", "qual": "EMBD", "base": null, "top": 55000, "from": 1784034300, "to": 1784048700, "series": "TANGO 9", "raw": "WSPA07 PHFO 141306\nSIGPAT\n\nKZAK SIGMET TANGO 9 VALID 141305/141705 PHFO-\nOAKLAND OCEANIC FIR EMBD TS OBS AT 1305Z WI N1330 W17115 - N0930\nW16315 - N0500 W16600 - N0900 W17315 - N1330 W17115. TOP FL550. STNR.\nNC."}, {"fir": "OAKLAND OCEANIC", "hazard": "TS", "qual": "FRQ", "base": null, "top": 53000, "from": 1784034600, "to": 1784049000, "series": "GOLF 52", "raw": "WSPN07 KKCI 141310\nSIGP0G\nKZAK SIGMET GOLF 52 VALID 141310/141710 KKCI-\nOAKLAND OCEANIC FIR FRQ TS OBS AT 1310Z WI N1547 W13010 - N0905\nW13311 - N0653 W13953 - N1309 W14008 - N1547 W13010. TOP FL530.\nSTNR. INTSF."}, {"fir": "NZZO AUCKLAND OCEANIC", "hazard": "ICE", "qual": "SEV", "base": 5000, "top": 15000, "from": 1784034480, "to": 1784048880, "series": "17", "raw": "WSPS21 NZKL 141305\nNZZO SIGMET 17 VALID 141308/141708 NZKL-\nNZZO AUCKLAND OCEANIC FIR SEV ICE FCST WI S6020 E17410 - S5530\nE17530 - S5310 E17900 - S5900 E17840 - S6310 W17710 - S6410 E17830 -\nS6020 E17410 5000FT/FL150 MOV SE 45KT NC="}, {"fir": "RPHI MANILA", "hazard": "VA", "qual": "MAYON", "base": null, "top": null, "from": 1784034660, "to": 1784056260, "series": "7", "raw": "WVPH31 RPLL 141311\nRPHI SIGMET 7 VALID 141311/141911 RPLL-\nRPHI MANILA FIR VA ERUPTION MT MAYON PSN N1315 E12341 \nVA CLD OBS AT 1253Z="}, {"fir": "NZZO AUCKLAND OCEANIC", "hazard": "TURB", "qual": "SEV", "base": 27000, "top": 37000, "from": 1784034660, "to": 1784049060, "series": "19", "raw": "WSPS21 NZKL 141309\nNZZO SIGMET 19 VALID 141311/141711 NZKL-\nNZZO AUCKLAND OCEANIC FIR SEV TURB FCST WI S2910 E17300 - S2830\nW16940 - S3030 W17210 - S3050 E17310 - S2910 E17300 FL270/370 STNR\nNC="}, {"fir": "ZWUQ URUMQI", "hazard": "TS", "qual": "EMBD", "base": null, "top": 34000, "from": 1784034720, "to": 1784049120, "series": "7", "raw": "WSCI39 ZWWW 141312\nZWUQ SIGMET 7 VALID 141312/141712 ZWWW - \nZWUQ URUMQI FIR EMBD TS FCST WI \nN4630 E08353 - N4423 E08625 - N4229 E08528 - \nN4427 E08053 - N4630 E08353\nTOP FL340 MOV NE 25KMH NC="}, {"fir": "VIDF DELHI", "hazard": "TS", "qual": "EMBD", "base": null, "top": 49000, "from": 1784034960, "to": 1784049360, "series": "1", "raw": "WSIN90 VIDP 141316\nVIDF SIGMET 1 VALID 141316/141716 VIDP- VIDF DELHI FIR EMBD TS OBS WI\n N2732 E08239 - N2708 E08133 - N2626 E08017 - N2805 E07907 - N2849\n E07941 - N2840 E08019 - N2732 E08239 TOP FL490 MOV SE 15KT NC="}, {"fir": "WBFC KOTA KINABALU", "hazard": "TS", "qual": "EMBD", "base": null, "top": 48000, "from": 1784035800, "to": 1784046600, "series": "4", "raw": "WSMS31 WMKK 141320\nWBFC SIGMET 4 VALID 141330/141630 WBKK-\nWBFC KOTA KINABALU FIR EMBD TS\nOBS WI N0116 E11428 - N0409 E11343 - N0722 E11558 - N0737 E11725 - N0632 E11812 - N0116 E11428 TOP FL480 MOV W 15KT NC="}, {"fir": "YBBB BRISBANE", "hazard": "TS", "qual": "FRQ", "base": null, "top": 35000, "from": 1784035320, "to": 1784038920, "series": "G01", "raw": "WSAU21 YMMC 141322\nYBBB SIGMET G01 VALID 141322/141422 YMMC-\nYBBB BRISBANE FIR FRQ TS OBS WI S3440 E16300 - S3500 E16140 - S3350\nE16040 - S3330 E16120 - S3350 E16230 - S3130 E16100 - S3120 E16200 -\nS3220 E16300 TOP FL350 MOV ESE 20KT NC="}, {"fir": "GOOO DAKAR TERRESTRE", "hazard": null, "qual": "SQL", "base": null, "top": 45000, "from": 1784035500, "to": 1784049900, "series": "B05", "raw": "WSSG31 GOOY 141309\nGOOO SIGMET B05 VALID 141325/141725 GOBD-\nGOOO DAKAR TERRESTRE FIR/UIR SQL OBS AT 1315Z\nS OF LINE  N1703 W01552 - N1708 W01047 TOP FL450 MOV W 45KT WKN="}, {"fir": "LJLA LJUBLJANA", "hazard": "TS", "qual": "FRQ", "base": null, "top": 42000, "from": 1784035800, "to": 1784044800, "series": "T01", "raw": "WSLJ31 LJLJ 141320\nLJLA SIGMET T01 VALID 141330/141600 LJLJ-\nLJLA LJUBLJANA FIR FRQ TS FCST WI N4608 E01319 - N4636 E01329 -\nN4644 E01538 - N4620 E01528 - N4611 E01434 - N4608 E01319 TOP FL420\nNC FCST AT 1600Z WI N4541 E01535 - N4541 E01536 - N4554 E01437 -\nN4644 E01518 - N4659 E01620 - N4628 E01641 - N4541 E01535="}, {"fir": "EPWW WARSZAWA", "hazard": "TS", "qual": "FRQ", "base": null, "top": 38000, "from": 1784035920, "to": 1784041200, "series": "T02", "raw": "WSPL31 EPWA 141332\nEPWW SIGMET T02 VALID 141332/141500 EPWA-\nEPWW WARSZAWA FIR FRQ TSGR FCST WI N4925 E02142 - N5014 E02105 -\nN5000 E01856 - N5052 E01841 - N5100 E02033 - N5041 E02329 - N4925\nE02142 TOP FL380 STNR INTSF="}, {"fir": "ZYSH SHENYANG", "hazard": "TS", "qual": "EMBD", "base": null, "top": 34000, "from": 1784036400, "to": 1784050800, "series": "3", "raw": "WSCI38 ZYTX 141332\nZYSH SIGMET 3 VALID 141340/141740 ZYTX-\nZYSH SHENYANG FIR EMBD TS FCST\nWI N4609 E11911 - N4713 E12209 - N4614 E12350 - N4445 E12052 - N4609\n E11911 TOP FL340 MOV NE 30KMH NC ="}], "nhc": [], "jtwc": [], "updated": "2026-07-14T13:42:43+00:00"}